easy_trilateration/graph.py
easy_trilateration/least_squares.py
easy_trilateration/model.py
easy_trilateration-0.1.4.dist-info/LICENSE
easy_trilateration-0.1.4.dist-info/METADATA
easy_trilateration-0.1.4.dist-info/WHEEL
easy_trilateration-0.1.4.dist-info/top_level.txt
easy_trilateration-0.1.4.dist-info/RECORD
