Metadata-Version: 2.1
Name: easy-trilateration
Version: 0.1.4
Summary: Easy Least-Squares trilateration using scipy
Home-page: https://github.com/agusalex/Least-Squares-Trilateration
Author: Agustin Alexander
Author-email: agustin.c.alexander@gmail.com
License: MIT
Platform: UNKNOWN
Classifier: Development Status :: 1 - Planning
Classifier: Intended Audience :: Science/Research
License-File: LICENSE
